{"nodes": [{"id": "avatar_04_male_sunglasses", "label": "Avatar 04 - Illustrated Male with Sunglasses", "file_type": "image", "source_file": "public 23.35.11/avatars/04.png", "source_location": null, "source_url": null, "captured_at": null, "author": null, "contributor": null}], "edges": [{"source": "avatar_04_male_sunglasses", "target": "concept_user_avatar_set", "relation": "references", "confidence": "EXTRACTED", "confidence_score": 1.0, "source_file": "public 23.35.11/avatars/04.png", "source_location": null, "weight": 1.0}], "hyperedges": []}